arbtt_chart.py
arbtt_chart-1.0.2.dist-info/LICENSE
arbtt_chart-1.0.2.dist-info/METADATA
arbtt_chart-1.0.2.dist-info/WHEEL
arbtt_chart-1.0.2.dist-info/entry_points.txt
arbtt_chart-1.0.2.dist-info/top_level.txt
arbtt_chart-1.0.2.dist-info/RECORD
