Metadata-Version: 2.1
Name: arbtt-chart
Version: 1.0.2
Summary: "Plot charts from arbtt-stats to terminal"
Author-email: Tomáš Janoušek <tomi@nomi.cz>
License: MIT
Project-URL: Homepage, https://github.com/liskin/arbtt-chart
Classifier: Development Status :: 5 - Production/Stable
Classifier: Environment :: Console
Classifier: License :: OSI Approved :: MIT License
Classifier: Operating System :: OS Independent
Classifier: Programming Language :: Python :: 3.7
Classifier: Programming Language :: Python :: 3.8
Classifier: Programming Language :: Python :: 3.9
Classifier: Programming Language :: Python :: 3.10
Classifier: Programming Language :: Python :: 3.11
Classifier: Topic :: Utilities
Requires-Python: ~=3.7
License-File: LICENSE
Requires-Dist: pandas (>=1.0.0)
Provides-Extra: dev
Requires-Dist: build (>=0.7) ; extra == 'dev'
Requires-Dist: cram ; extra == 'dev'
Requires-Dist: flake8 (>=3.7.0) ; extra == 'dev'
Requires-Dist: isort (>=5.0) ; extra == 'dev'
Requires-Dist: mypy (>=0.900) ; extra == 'dev'
Requires-Dist: twine ; extra == 'dev'
Provides-Extra: test
Requires-Dist: pytest ; extra == 'test'
